vexparser/__init__.py
vexparser/__main__.py
vexparser/callback_manager.py
vexparser/classification_parser.py
vexparser/mark_parser.py
vexparser/messaging.py
vexparser/util.py
vexparser-0.3.1.dist-info/DESCRIPTION.rst
vexparser-0.3.1.dist-info/METADATA
vexparser-0.3.1.dist-info/RECORD
vexparser-0.3.1.dist-info/WHEEL
vexparser-0.3.1.dist-info/entry_points.txt
vexparser-0.3.1.dist-info/metadata.json
vexparser-0.3.1.dist-info/top_level.txt
