Metadata-Version: 2.0
Name: vexparser
Version: 0.3.1
Summary: Command parsing for vexbot
Home-page: https://github.com/benhoff/commandparser
Author: Ben Hoff
Author-email: beohoff@gmail.com
License: GPL3
Keywords: command parsing intent classifier
Platform: UNKNOWN
Classifier: Development Status :: 1 - Planning
Classifier: Intended Audience :: Developers
Classifier: License :: OSI Approved :: GNU General Public License v3 (GPLv3)
Classifier: Programming Language :: Python :: 3
Classifier: Programming Language :: Python :: 3.5
Classifier: Topic :: Utilities
Classifier: Operating System :: OS Independent
Requires-Dist: nltk
Requires-Dist: numpy
Requires-Dist: pluginmanager
Requires-Dist: pyyaml
Requires-Dist: pyzmq
Requires-Dist: textblob
Requires-Dist: vexmessage
Provides-Extra: dev
Requires-Dist: flake8; extra == 'dev'
